Workbook

Sheet 基本項目
A1: 共通 | B1: 見積依頼日
A2: 共通 | B2: 見積日
A3: 共通 | B3: 発注日
A4: 共通 | B4: 請求日
A5: 共通 | B5: 納品日
A6: 共通 | B6: 振込先
A7: 共通 | B7: 支払い方法
A8: 共通 | B8: 納品場所
A9: 共通 | B9: 納期
A10: 発注者 | B10: 会社名
A11: 発注者 | B11: 郵便番号
A12: 発注者 | B12: 住所
... A21: 受注者 | B21: 担当者名

Sheet 見積依頼書
A1: 見積依頼書
L3: 見積依頼日 | N3: ='基本項目'!C1
L4: 見積依頼番号 | N4: =TEXT(N3,"yyyymm") & "-" & TEXT(DAY(N3),"00") -> 189912-30
A5: ='基本項目'!C16 | J5: 御中
A6: ='基本項目'!C17
A7: ='基本項目'!C18 | K7: ='基本項目'!C10
A8: ='基本項目'!C19 | K8: ='基本項目'!C11
K9: 住所： | L9: ='基本項目'!C12
A10: 下記の通り、見積を依頼します | K10: 電話： | L10: ='基本項目'!C13
A11: 納期 | B11: 44985 | K11: メール： | L11: ='基本項目'!C14
A12: 納品場所 | B12: =L9 | K12: 担当者名： | L12: ='基本項目'!C15
A13: 支払い方法 | B13: ='基本項目'!C7
A15: 内容 | J15: 数量 | K15: 単位 | L15: サイズや要望など
A16: ='見積書'!A19 -> 採用研修事業サイト制作（企画・原稿・デザイン） | J16: ='見積書'!K19 | K16: ='見積書'!L19 -> 個
A17: ='見積書'!A20 -> (内訳) | J17: ='見積書'!K20 | K17: ='見積書'!L20 -> 個
A18: ='見積書'!A21 -> TOPページ制作 | J18: ='見積書'!K21 -> 1 | K18: ='見積書'!L21 -> 個
A19: ='見積書'!A22 -> 資料請求ページ制作 | J19: ='見積書'!K22 -> 1 | K19: ='見積書'!L22 -> 個
A20: ='見積書'!A23 -> セミナー集客ページ制作 | J20: ='見積書'!K23 -> 1 | K20: ='見積書'!L23 -> 個
A21: ='見積書'!A24 -> オンライン研修案内用ページ制作 | J21: ='見積書'!K24 -> 3 | K21: ='見積書'!L24 -> 個
A22: ='見積書'!A25 -> コンサルティング案内用ページ制作 | J22: ='見積書'!K25 -> 1 | K22: ='見積書'!L25 -> 個
A23: ='見積書'!A26 -> お問い合わせ獲得用ページ制作 | J23: ='見積書'!K26 -> 1 | K23: ='見積書'!L26 -> 個
A24: ='見積書'!A27 -> お問い合わせ時配布用資料作成 | J24: ='見積書'!K27 -> 1 | K24: ='見積書'!L27 -> 個
A25: ='見積書'!A28 -> ブログ記事制作 | J25: ='見積書'!K28 -> 30 | K25: ='見積書'!L28 -> 個
A26: ='見積書'!A29 -> ウェビナー制作 | J26: ='見積書'!K29 -> 1 | K26: ='見積書'!L29 -> 個
A27: ='見積書'!A30 -> Easy Webinar | J27: ='見積書'!K30 -> 1 | K27: ='見積書'!L30 -> 個
... A30: ='見積書'!A33 | J30: ='見積書'!K33 | K30: ='見積書'!L33 -> 個
A32: 備考・見積書のお届け先等
A33: 納品場所
A34: 会社名 | B34: 相生株式会社

Sheet 見積書
A1: 見積書
M3: 見積日 | O3: ='基本項目'!C2
M4: 見積番号 | O4: =TEXT(O3,"yyyymm") & "-" & TEXT(DAY(O3),"00") -> 189912-30
A5: ='基本項目'!C10 | J5: 御中
A6: ='基本項目'!C11
A7: ='基本項目'!C12 | L7: ='基本項目'!C16
L8: ='基本項目'!C17
A9: 下記の通り、発注いたします。 | L9: 住所： | M9: ='基本項目'!C18
A10: 合計金額（税込） | L10: 電話： | M10: ='基本項目'!C19
A11: =P36 -> 2090000 | L11: メール： | M11: ='基本項目'!C20
L12: 担当者： | M12: ='基本項目'!C21
A14: 納期 | B14: 44985
A15: 納品場所 | B15: =A7
A18: 内容 | J18: 軽減税率 | K18: 数量 | L18: 単位 | M18: 単価（税抜） | O18: 税率 | P18: 金額（税抜）
A19: 採用研修事業サイト制作（企画・原稿・デザイン） | J19: --- | L19: 個 | O19: 0.1 | P19: =K19*M19 -> 0
A20: (内訳) | J20: --- | L20: 個 | O20: 0.1 | P20: =K20*M20 -> 0
A21: TOPページ制作 | J21: --- | K21: 1 | L21: 個 | M21: 200000 | O21: 0.1 | P21: =K21*M21 -> 200000
A22: 資料請求ページ制作 | J22: --- | K22: 1 | L22: 個 | M22: 200000 | O22: 0.1 | P22: =K22*M22 -> 200000
A23: セミナー集客ページ制作 | J23: --- | K23: 1 | L23: 個 | M23: 100000 | O23: 0.1 | P23: =K23*M23 -> 100000
A24: オンライン研修案内用ページ制作 | J24: --- | K24: 3 | L24: 個 | M24: 100000 | O24: 0.1 | P24: =K24*M24 -> 300000
A25: コンサルティング案内用ページ制作 | J25: --- | K25: 1 | L25: 個 | M25: 100000 | O25: 0.1 | P25: =K25*M25 -> 100000
A26: お問い合わせ獲得用ページ制作 | J26: --- | K26: 1 | L26: 個 | M26: 100000 | O26: 0.1 | P26: =K26*M26 -> 100000
A27: お問い合わせ時配布用資料作成 | J27: --- | K27: 1 | L27: 個 | M27: 300000 | O27: 0.1 | P27: =K27*M27 -> 300000
A28: ブログ記事制作 | J28: --- | K28: 30 | L28: 個 | M28: 10000 | O28: 0.1 | P28: =K28*M28 -> 300000
A29: ウェビナー制作 | J29: --- | K29: 1 | L29: 個 | M29: 200000 | O29: 0.1 | P29: =K29*M29 -> 200000
A30: Easy Webinar | J30: --- | K30: 1 | L30: 個 | M30: 100000 | O30: 0.1 | P30: =K30*M30 -> 100000
J31: --- | L31: 個 | O31: 0.1 | P31: =K31*M31 -> 0
J32: --- | L32: 個 | O32: 0.1 | P32: =K32*M32 -> 0
J33: --- | L33: 個 | O33: 0.1 | P33: =K33*M33 -> 0
N34: 小計 | P34: =SUM(P19:Q33) -> 1900000
N35: 消費税 | P35: =P34*0.1 -> 190000
N36: 合計 | P36: =P34+P35 -> 2090000
A40: 備考

Sheet 発注書
B1: 発注書
N3: 発注日 | P3: ='基本項目'!C3
N4: 発注番号 | P4: =TEXT(P3,"yyyymm") & "-" & TEXT(DAY(P3),"00") -> 189912-30
B5: ='基本項目'!C16 | K5: 御中
B6: ='基本項目'!C17
B7: ='基本項目'!C18 | M7: ='基本項目'!C10
M8: ='基本項目'!C11
B9: 下記の通り、発注いたします。 | M9: 住所： | N9: ='基本項目'!C12
B10: 合計金額（税込） | M10: 電話： | N10: ='基本項目'!C13
B11: =Q36 -> 0 | M11: メール： | N11: ='基本項目'!C14
M12: 担当者： | N12: ='基本項目'!C15
B14: 納期 | C14: ='見積書'!B14 -> 44985
B15: 納品場所 | C15: ='基本項目'!C12
B18: 内容 | K18: 軽減税率 | L18: 数量 | M18: 単位 | N18: 単価（税抜） | P18: 税率 | Q18: 金額（税抜）
B19: ='見積書'!A19 -> 採用研修事業サイト制作（企画・原稿・デザイン） | K19: ='見積書'!J19 -> --- | L19: ='見積書'!K19 | M19: ='見積書'!L19 -> 個 | N19: ='見積書'!M19 | P19: 0.1 | Q19: =L19*N19 -> 0
B20: ='見積書'!A20 -> (内訳) | K20: ='見積書'!J20 -> --- | L20: ='見積書'!K20 | M20: ='見積書'!L20 -> 個 | N20: ='見積書'!M20 | P20: 0.1 | Q20: =L20*N20 -> 0
B21: ='見積書'!A21 -> TOPページ制作 | K21: ='見積書'!J21 -> --- | L21: ='見積書'!K21 -> 1 | M21: ='見積書'!L21 -> 個 | N21: ='見積書'!M21 -> 200000 | P21: 0.1 | Q21: =L21*N21 -> 200000
B22: ='見積書'!A22 -> 資料請求ページ制作 | K22: ='見積書'!J22 -> --- | L22: ='見積書'!K22 -> 1 | M22: ='見積書'!L22 -> 個 | N22: ='見積書'!M22 -> 200000 | P22: 0.1 | Q22: =L22*N22 -> 200000
B23: ='見積書'!A23 -> セミナー集客ページ制作 | K23: ='見積書'!J23 -> --- | L23: ='見積書'!K23 -> 1 | M23: ='見積書'!L23 -> 個 | N23: ='見積書'!M23 -> 100000 | P23: 0.1 | Q23: =L23*N23 -> 100000
B24: ='見積書'!A24 -> オンライン研修案内用ページ制作 | K24: ='見積書'!J24 -> --- | L24: ='見積書'!K24 -> 3 | M24: ='見積書'!L24 -> 個 | N24: ='見積書'!M24 -> 100000 | P24: 0.1 | Q24: =L24*N24 -> 300000
B25: ='見積書'!A25 -> コンサルティング案内用ページ制作 | K25: ='見積書'!J25 -> --- | L25: ='見積書'!K25 -> 1 | M25: ='見積書'!L25 -> 個 | N25: ='見積書'!M25 -> 100000 | P25: 0.1 | Q25: =L25*N25 -> 100000
B26: ='見積書'!A26 -> お問い合わせ獲得用ページ制作 | K26: ='見積書'!J26 -> --- | L26: ='見積書'!K26 -> 1 | M26: ='見積書'!L26 -> 個 | N26: ='見積書'!M26 -> 100000 | P26: 0.1 | Q26: =L26*N26 -> 100000
B27: ='見積書'!A27 -> お問い合わせ時配布用資料作成 | K27: ='見積書'!J27 -> --- | L27: ='見積書'!K27 -> 1 | M27: ='見積書'!L27 -> 個 | N27: ='見積書'!M27 -> 300000 | P27: 0.1 | Q27: =L27*N27 -> 300000
B28: ='見積書'!A28 -> ブログ記事制作 | K28: ='見積書'!J28 -> --- | L28: ='見積書'!K28 -> 30 | M28: ='見積書'!L28 -> 個 | N28: ='見積書'!M28 -> 10000 | P28: 0.1 | Q28: =L28*N28 -> 300000
B29: ='見積書'!A29 -> ウェビナー制作 | K29: ='見積書'!J29 -> --- | L29: ='見積書'!K29 -> 1 | M29: ='見積書'!L29 -> 個 | N29: ='見積書'!M29 -> 200000 | P29: 0.1 | Q29: =L29*N29 -> 200000
B30: ='見積書'!A30 -> Easy Webinar | K30: ='見積書'!J30 -> --- | L30: ='見積書'!K30 -> 1 | M30: ='見積書'!L30 -> 個 | N30: ='見積書'!M30 -> 100000 | P30: 0.1 | Q30: =L30*N30 -> 100000
... B33: ='見積書'!A33 | K33: ='見積書'!J33 -> --- | L33: ='見積書'!K33 | M33: ='見積書'!L33 -> 個 | N33: ='見積書'!M33 | P33: 0.1 | Q33: =L33*N33 -> 0
O34: 小計 | Q34: =L34*N34 -> 0
O35: 消費税 | Q35: =L35*N35 -> 0
O36: 合計 | Q36: =L36*N36 -> 0
B40: 備考

Sheet 請求書
A1: 請求書
A2: ='見積書'!A2
M3: 請求日 | O3: ='見積書'!O3
M4: 請求書番号 | O4: ='見積書'!O4 -> 189912-30
A5: ='見積書'!A5 | J5: 御中
A6: ='基本項目'!C11
A7: ='基本項目'!C12 | L7: ='見積書'!L7
L8: ='見積書'!L8
A9: 下記の通り、発注いたします。 | L9: 住所： | M9: ='見積書'!M9
A10: 合計金額（税込） | L10: 電話： | M10: ='見積書'!M10
A11: =P36 -> 2090000 | L11: メール： | M11: ='見積書'!M11
L12: 担当者： | M12: ='見積書'!M12
A14: 納期 | B14: ='見積書'!B14 -> 44985
A15: 納品場所 | B15: ='見積書'!B15
A18: 内容 | J18: 軽減税率 | K18: 数量 | L18: 単位 | M18: 単価（税抜） | O18: 税率 | P18: 金額（税抜）
A19: ='見積書'!A19 -> 採用研修事業サイト制作（企画・原稿・デザイン） | J19: ='見積書'!J19 -> --- | K19: ='見積書'!K19 | L19: ='見積書'!L19 -> 個 | M19: ='見積書'!M19 | O19: 0.1 | P19: =K19*M19 -> 0
A20: ='見積書'!A20 -> (内訳) | J20: ='見積書'!J20 -> --- | K20: ='見積書'!K20 | L20: ='見積書'!L20 -> 個 | M20: ='見積書'!M20 | O20: 0.1 | P20: =K20*M20 -> 0
A21: ='見積書'!A21 -> TOPページ制作 | J21: ='見積書'!J21 -> --- | K21: ='見積書'!K21 -> 1 | L21: ='見積書'!L21 -> 個 | M21: ='見積書'!M21 -> 200000 | O21: 0.1 | P21: =K21*M21 -> 200000
A22: ='見積書'!A22 -> 資料請求ページ制作 | J22: ='見積書'!J22 -> --- | K22: ='見積書'!K22 -> 1 | L22: ='見積書'!L22 -> 個 | M22: ='見積書'!M22 -> 200000 | O22: 0.1 | P22: =K22*M22 -> 200000
A23: ='見積書'!A23 -> セミナー集客ページ制作 | J23: ='見積書'!J23 -> --- | K23: ='見積書'!K23 -> 1 | L23: ='見積書'!L23 -> 個 | M23: ='見積書'!M23 -> 100000 | O23: 0.1 | P23: =K23*M23 -> 100000
A24: ='見積書'!A24 -> オンライン研修案内用ページ制作 | J24: ='見積書'!J24 -> --- | K24: ='見積書'!K24 -> 3 | L24: ='見積書'!L24 -> 個 | M24: ='見積書'!M24 -> 100000 | O24: 0.1 | P24: =K24*M24 -> 300000
A25: ='見積書'!A25 -> コンサルティング案内用ページ制作 | J25: ='見積書'!J25 -> --- | K25: ='見積書'!K25 -> 1 | L25: ='見積書'!L25 -> 個 | M25: ='見積書'!M25 -> 100000 | O25: 0.1 | P25: =K25*M25 -> 100000
A26: ='見積書'!A26 -> お問い合わせ獲得用ページ制作 | J26: ='見積書'!J26 -> --- | K26: ='見積書'!K26 -> 1 | L26: ='見積書'!L26 -> 個 | M26: ='見積書'!M26 -> 100000 | O26: 0.1 | P26: =K26*M26 -> 100000
A27: ='見積書'!A27 -> お問い合わせ時配布用資料作成 | J27: ='見積書'!J27 -> --- | K27: ='見積書'!K27 -> 1 | L27: ='見積書'!L27 -> 個 | M27: ='見積書'!M27 -> 300000 | O27: 0.1 | P27: =K27*M27 -> 300000
A28: ='見積書'!A28 -> ブログ記事制作 | J28: ='見積書'!J28 -> --- | K28: ='見積書'!K28 -> 30 | L28: ='見積書'!L28 -> 個 | M28: ='見積書'!M28 -> 10000 | O28: 0.1 | P28: =K28*M28 -> 300000
A29: ='見積書'!A29 -> ウェビナー制作 | J29: ='見積書'!J29 -> --- | K29: ='見積書'!K29 -> 1 | L29: ='見積書'!L29 -> 個 | M29: ='見積書'!M29 -> 200000 | O29: 0.1 | P29: =K29*M29 -> 200000
A30: ='見積書'!A30 -> Easy Webinar | J30: ='見積書'!J30 -> --- | K30: ='見積書'!K30 -> 1 | L30: ='見積書'!L30 -> 個 | M30: ='見積書'!M30 -> 100000 | O30: 0.1 | P30: =K30*M30 -> 100000
... A32: ='見積書'!A32 | J32: ='見積書'!J32 -> --- | K32: ='見積書'!K32 | L32: ='見積書'!L32 -> 個 | M32: ='見積書'!M32 | O32: 0.1 | P32: =K32*M32 -> 0
A33: ='見積書'!A33 | K33: ='見積書'!K33 | L33: ='見積書'!L33 -> 個 | M33: ='見積書'!M33 | O33: 0.1 | P33: =K33*M33 -> 0
N34: 小計 | P34: =SUM(P19:Q33) -> 1900000
N35: 消費税 | P35: =P34*0.1 -> 190000
N36: 合計 | P36: =P34+P35 -> 2090000
A40: 備考
A41: お振込先 | B41: ='基本項目'!C6
A42: ※お振込手数料は御社負担にてお願いいたします。

Sheet 納品書
A1: 納品書
M3: 納品日 | O3: 44927
M4: 納品番号 | O4: =TEXT(O3,"yyyymm") & "-" & TEXT(DAY(O3),"00") -> 202301-01
A5: ='基本項目'!C10 | J5: 御中
A6: ='基本項目'!C11
A7: ='基本項目'!C12 | L7: ='基本項目'!C16
L8: ='基本項目'!C17
A9: 下記の通り、納品を確認しました | L9: 住所： | M9: ='基本項目'!C18
A10: 合計金額（税込） | L10: 電話： | M10: ='基本項目'!C19
A11: =P36 -> 2090000 | L11: メール： | M11: ='基本項目'!C20
L12: 担当者： | M12: ='基本項目'!C21
A14: 納品日 | B14: =O3 -> 44927
A15: 納品場所 | B15: =A7
A18: 内容 | J18: 軽減税率 | K18: 数量 | L18: 単位 | M18: 単価（税抜） | O18: 税率 | P18: 金額（税抜）
A19: ='見積書'!A19 -> 採用研修事業サイト制作（企画・原稿・デザイン） | J19: --- | K19: ='見積書'!K19 | L19: 個 | M19: ='見積書'!M19 | O19: 0.1 | P19: =K19*M19 -> 0
A20: ='見積書'!A20 -> (内訳) | K20: ='見積書'!K20 | L20: 個 | M20: ='見積書'!M20 | O20: 0.1 | P20: =K20*M20 -> 0
A21: ='見積書'!A21 -> TOPページ制作 | K21: ='見積書'!K21 -> 1 | L21: 個 | M21: ='見積書'!M21 -> 200000 | O21: 0.1 | P21: =K21*M21 -> 200000
A22: ='見積書'!A22 -> 資料請求ページ制作 | K22: ='見積書'!K22 -> 1 | L22: 個 | M22: ='見積書'!M22 -> 200000 | O22: 0.1 | P22: =K22*M22 -> 200000
A23: ='見積書'!A23 -> セミナー集客ページ制作 | K23: ='見積書'!K23 -> 1 | L23: 個 | M23: ='見積書'!M23 -> 100000 | O23: 0.1 | P23: =K23*M23 -> 100000
A24: ='見積書'!A24 -> オンライン研修案内用ページ制作 | K24: ='見積書'!K24 -> 3 | L24: 個 | M24: ='見積書'!M24 -> 100000 | O24: 0.1 | P24: =K24*M24 -> 300000
A25: ='見積書'!A25 -> コンサルティング案内用ページ制作 | K25: ='見積書'!K25 -> 1 | L25: 個 | M25: ='見積書'!M25 -> 100000 | O25: 0.1 | P25: =K25*M25 -> 100000
A26: ='見積書'!A26 -> お問い合わせ獲得用ページ制作 | K26: ='見積書'!K26 -> 1 | L26: 個 | M26: ='見積書'!M26 -> 100000 | O26: 0.1 | P26: =K26*M26 -> 100000
A27: ='見積書'!A27 -> お問い合わせ時配布用資料作成 | K27: ='見積書'!K27 -> 1 | L27: 個 | M27: ='見積書'!M27 -> 300000 | O27: 0.1 | P27: =K27*M27 -> 300000
A28: ='見積書'!A28 -> ブログ記事制作 | K28: ='見積書'!K28 -> 30 | L28: 個 | M28: ='見積書'!M28 -> 10000 | O28: 0.1 | P28: =K28*M28 -> 300000
A29: ='見積書'!A29 -> ウェビナー制作 | K29: ='見積書'!K29 -> 1 | L29: 個 | M29: ='見積書'!M29 -> 200000 | O29: 0.1 | P29: =K29*M29 -> 200000
A30: ='見積書'!A30 -> Easy Webinar | K30: ='見積書'!K30 -> 1 | L30: 個 | M30: ='見積書'!M30 -> 100000 | O30: 0.1 | P30: =K30*M30 -> 100000
A31: ='見積書'!A31 | K31: ='見積書'!K31 | L31: 個 | M31: ='見積書'!M31 | O31: 0.1 | P31: =K31*M31 -> 0
... A33: ='見積書'!A33 | K33: ='見積書'!K33 | L33: 個 | M33: ='見積書'!M33 | O33: 0.1 | P33: =K33*M33 -> 0
N34: 小計 | P34: =SUM(P19:Q33) -> 1900000
N35: 消費税 | P35: =P34*0.1 -> 190000
N36: 合計 | P36: =P34+P35 -> 2090000
A40: 備考
